fastlab/__init__.py
fastlab/__version__.py
fastlab/logging.py
fastlab/decorators/__init__.py
fastlab/decorators/config.py
fastlab/decorators/log.py
fastlab/models/__init__.py
fastlab/routers/__init__.py
fastlab/routers/health.py
fastlab/utils/__init__.py
fastlab/utils/time.py
fastlab-0.3.0.dist-info/LICENSE
fastlab-0.3.0.dist-info/METADATA
fastlab-0.3.0.dist-info/WHEEL
fastlab-0.3.0.dist-info/top_level.txt
fastlab-0.3.0.dist-info/RECORD
