Metadata-Version: 2.1
Name: fastlab
Version: 0.3.0
Summary: An extension library for FastAPI framework
Home-page: https://github.com/tezignlab/fastlab
Author: Anoyi
Author-email: anoyi@qq.com
License: MIT License
Keywords: fastapi logs utils models routers decorators
Classifier: Development Status :: 4 - Beta
Classifier: Environment :: Web Environment
Classifier: Intended Audience :: Developers
Classifier: License :: OSI Approved :: MIT License
Classifier: Programming Language :: Python
Classifier: Programming Language :: Python :: 3
Classifier: Programming Language :: Python :: 3.7
Classifier: Programming Language :: Python :: 3.8
Classifier: Programming Language :: Python :: 3.9
Classifier: Programming Language :: Python :: 3.10
Classifier: Programming Language :: Python :: 3.11
Classifier: Programming Language :: Python :: 3.12
Classifier: Topic :: Software Development :: Libraries :: Python Modules
License-File: LICENSE
Requires-Dist: fastapi >=0.78.0
Requires-Dist: PyYAML >=6.0
